aioflureedb/__init__.py
aioflureedb/domain_api.py
aioflureedb/signing.py
aioflureedb-0.2.13.dist-info/DESCRIPTION.rst
aioflureedb-0.2.13.dist-info/METADATA
aioflureedb-0.2.13.dist-info/RECORD
aioflureedb-0.2.13.dist-info/WHEEL
aioflureedb-0.2.13.dist-info/metadata.json
aioflureedb-0.2.13.dist-info/top_level.txt
