Metadata-Version: 2.0
Name: aioflureedb
Version: 0.2.13
Summary: Asynchonous library for usage of the FlureeDB API
Home-page: https://github.com/pibara/aioflureedb
Author: Rob J Meijer
Author-email: pibara@gmail.com
License: BSD
Keywords: flureedb fluree flureeql sparql graphql
Platform: UNKNOWN
Classifier: Development Status :: 4 - Beta
Classifier: Intended Audience :: Developers
Classifier: Topic :: Software Development :: Libraries
Classifier: License :: OSI Approved :: BSD License
Classifier: Programming Language :: Python :: 2
Classifier: Programming Language :: Python :: 2.7
Classifier: Operating System :: OS Independent
Classifier: Environment :: Other Environment
Requires-Dist: starkbank-ecdsa (==1.1.1)
Requires-Dist: aiohttp
Requires-Dist: base58
Requires-Dist: pyjsonata
